meta_ai_api/__init__.py
meta_ai_api/exceptions.py
meta_ai_api/main.py
meta_ai_api/utils.py
meta_ai_api-1.2.5.dist-info/METADATA
meta_ai_api-1.2.5.dist-info/WHEEL
meta_ai_api-1.2.5.dist-info/top_level.txt
meta_ai_api-1.2.5.dist-info/RECORD
