Metadata-Version: 2.1
Name: meta_ai_api
Version: 1.2.5
Summary: Meta AI API Wrapper to interact with the Meta AI API
Home-page: https://github.com/tomchen/example_pypi_package
Author: Roméo Phillips
Author-email: phillipsromeo@gmail.com
Project-URL: Documentation, https://github.com/Strvm/meta-ai-api
Project-URL: Bug Reports, https://github.com/Strvm/meta-ai-api
Project-URL: Source Code, https://github.com/Strvm/meta-ai-api
Keywords: llm,ai,meta_ai_api
Classifier: Development Status :: 5 - Production/Stable
Classifier: Intended Audience :: Developers
Classifier: Topic :: Software Development :: Build Tools
Classifier: Programming Language :: Python :: 3
Classifier: Programming Language :: Python :: 3.6
Classifier: Programming Language :: Python :: 3.7
Classifier: Programming Language :: Python :: 3.8
Classifier: Programming Language :: Python :: 3.9
Classifier: Programming Language :: Python :: 3 :: Only
Classifier: License :: OSI Approved :: MIT License
Classifier: Operating System :: OS Independent
Requires-Python: >=3.6
Requires-Dist: requests
Requires-Dist: requests-html
Requires-Dist: lxml_html_clean
Provides-Extra: dev
Requires-Dist: check-manifest; extra == "dev"
